LICENSE.txt
MANIFEST.in
README.rst
TODO
pavement.py
requirements.txt
setup.py
confduino/__init__.py
confduino/about.py
confduino/boardinstall.py
confduino/boardlist.py
confduino/boardremove.py
confduino/exampallcreate.py
confduino/exampallremove.py
confduino/examplist.py
confduino/hwpackinstall.py
confduino/hwpacklist.py
confduino/hwpackremove.py
confduino/libinstall.py
confduino/liblist.py
confduino/libremove.py
confduino/mculist.py
confduino/prettyprint.py
confduino/proginstall.py
confduino/proglist.py
confduino/progremove.py
confduino/util.py
confduino/version.py
confduino.egg-info/PKG-INFO
confduino.egg-info/SOURCES.txt
confduino.egg-info/dependency_links.txt
confduino.egg-info/not-zip-safe
confduino.egg-info/requires.txt
confduino.egg-info/top_level.txt
confduino/examples/__init__.py
confduino/examples/alt.py
confduino/examples/atmega88.py
confduino/examples/board.py
confduino/examples/custom_boards.py
confduino/examples/dapa.py
confduino/examples/metaboard.py
confduino/examples/ps2.py
confduino/examples/remove_boards.py
confduino/examples/remove_libraries.py
confduino/examples/sanguino.py
confduino/examples/stk200.py
confduino/examples/upgrademany.py
docs/api.rst
docs/conf.py
docs/dev.rst
docs/examples.rst
docs/index.rst
docs/links.rst
docs/menu.png
docs/readme.rst
docs/usage_all.rst
docs/usage_board.rst
docs/usage_lib.rst
docs/usage_path.rst
docs/usage_prog.rst
docs/usage_version.rst