Metadata-Version: 1.1
Name: confduino
Version: 0.2.3
Summary: Arduino software configurator
Home-page: https://github.com/ponty/confduino
Author: ponty
Author-email: UNKNOWN
License: BSD
Keywords: arduino
Platform: UNKNOWN
Classifier: License :: OSI Approved :: BSD License
Classifier: Natural Language :: English
Classifier: Operating System :: OS Independent
Classifier: Programming Language :: Python
Classifier: Programming Language :: Python :: 2
Classifier: Programming Language :: Python :: 2.6
Classifier: Programming Language :: Python :: 2.7
Classifier: Programming Language :: Python :: 3
Classifier: Programming Language :: Python :: 3.3
Classifier: Programming Language :: Python :: 3.4
